lrts/__init__.py
lrts/cli.py
lrts/service.py
lrts/communication/__init__.py
lrts/communication/ipc_message.py
lrts/communication/node.py
lrts/communication/application/__init__.py
lrts/communication/application/application.py
lrts/communication/application/application_information.py
lrts/communication/application/zmq_application.py
lrts/communication/progress/__init__.py
lrts/communication/progress/progress_client.py
lrts/communication/progress/progress_client_information.py
lrts/communication/progress/progress_requests.py
lrts/communication/progress/progress_server.py
lrts/communication/progress/zmq_progress_client.py
lrts/communication/progress/zmq_progress_server.py
lrts/communication/router/__init__.py
lrts/communication/router/application_router.py
lrts/communication/router/progress_client_router.py
lrts/communication/router/progress_server_router.py
lrts/communication/router/scheduler_router.py
lrts/communication/router/worker_router.py
lrts/communication/router/zmq_application_router.py
lrts/communication/router/zmq_progress_client_router.py
lrts/communication/router/zmq_progress_server_router.py
lrts/communication/router/zmq_scheduler_router.py
lrts/communication/router/zmq_worker_router.py
lrts/communication/scheduler/__init__.py
lrts/communication/scheduler/scheduler.py
lrts/communication/scheduler/zmq_scheduler.py
lrts/communication/util/__init__.py
lrts/communication/util/zmq_net_traffic_utils.py
lrts/communication/worker/__init__.py
lrts/communication/worker/worker.py
lrts/communication/worker/worker_information.py
lrts/communication/worker/zmq_worker.py
lrts/examples/__init__.py
lrts/examples/applications/__init__.py
lrts/examples/applications/async_as_completed_example.py
lrts/examples/applications/detailed_progress_bars.py
lrts/examples/applications/example_application.py
lrts/examples/applications/synchronous_example.py
lrts/examples/applications/synchronous_multi_example.py
lrts/examples/services/__init__.py
lrts/examples/services/mult_service.py
lrts-0.1.0.dist-info/LICENSE
lrts-0.1.0.dist-info/METADATA
lrts-0.1.0.dist-info/WHEEL
lrts-0.1.0.dist-info/entry_points.txt
lrts-0.1.0.dist-info/top_level.txt
lrts-0.1.0.dist-info/RECORD
