Metadata-Version: 2.1
Name: lrts
Version: 0.1.0
Summary: A python distributed task computation library.
Home-page: https://github.com/RobertEngen/lrts
Author: Robert Engen
Author-email: rnengen@gmail.com
License-File: LICENSE
Requires-Dist: pyzmq
Provides-Extra: detailed_progress
Requires-Dist: enlighten ; extra == 'detailed_progress'
Requires-Dist: loguru ; extra == 'detailed_progress'
